testai_classifier/__init__.py
testai_classifier/classifier_pb2.py
testai_classifier/classifier_pb2_grpc.py
testai_classifier/client.py
testai_classifier-1.1.0.dist-info/LICENSE
testai_classifier-1.1.0.dist-info/METADATA
testai_classifier-1.1.0.dist-info/WHEEL
testai_classifier-1.1.0.dist-info/top_level.txt
testai_classifier-1.1.0.dist-info/RECORD
