Metadata-Version: 2.1
Name: testai-classifier
Version: 1.1.0
Summary: This is a client for the Test.ai classifier RPC server, which allows direct use of the classifier via a Python API and also provides a helper method for use with Selenium.
Home-page: https://github.com/testdotai/classifier-client-python
Author: Jonathan Lipps
Author-email: jlipps@cloudgrey.io
License: UNKNOWN
Keywords: selenium appium ai ml
Platform: UNKNOWN
Classifier: Programming Language :: Python :: 3
Classifier: License :: OSI Approved :: Apache Software License
Classifier: Operating System :: OS Independent
Requires-Python: >=3.7
Requires-Dist: grpcio
